LICENSE
MANIFEST.in
README.md
pavement.py
requirements-dev.txt
requirements.txt
setup.py
tox.ini
docs/Makefile
docs/make.bat
docs/source/README
docs/source/conf.py
docs/source/index.rst
docs/source/_static/.gitkeep
nssm/__init__.py
nssm/cli.py
nssm/configuration.py
nssm/exceptions.py
nssm/metadata.py
nssm/parameters.py
nssm/service.py
nssm/wrapper.py
nssm/abstract/__init__.py
nssm/abstract/collections.py
nssm/bin/win32/nssm.exe
nssm/bin/win64/nssm.exe
pynssm.egg-info/PKG-INFO
pynssm.egg-info/SOURCES.txt
pynssm.egg-info/dependency_links.txt
pynssm.egg-info/not-zip-safe
pynssm.egg-info/requires.txt
pynssm.egg-info/top_level.txt